{
    "homes": [
        {
            "id": "1001",
            "type": "home",
            "city": {
                "id": "2001",
                "name": "Bogotá",
                "country": "Colombia"
            },
            "address": "Cra. 69f #4-65 a 4-5",
            "neighborhood": "Nueva Marsella",
            "lat": "4.626776",
            "lng": "-74.130639",
            "homeStatus": "sale",
            "bedrooms": "4",
            "bathrooms": "3",
            "price": "500000000",
            "area": "146",
            "desc": "Lorem, ipsum dolor sit amet consectetur adipisicing elit. Ipsam voluptatem nam ad doloribus ullam modi? Maxime nam voluptatem harum at iste, esse cum maiores! Distinctio eligendi praesentium facere atque est!"
        },
        {
            "id": "1002",
            "type": "home",
            "city": {
                "id": "2001",
                "name": "Bogotá",
                "country": "Colombia"
            },
            "address": "Cra. 69 Bis #4-2 a 4-66",
            "neighborhood": "Nueva Marsella",
            "lat": "4.626583",
            "lng": "-74.128665",
            "homeStatus": "sale",
            "bedrooms": "4",
            "bathrooms": "3",
            "price": "500000000",
            "area": "146",
            "desc": "Lorem, ipsum dolor sit amet consectetur adipisicing elit. Ipsam voluptatem nam ad doloribus ullam modi? Maxime nam voluptatem harum at iste, esse cum maiores! Distinctio eligendi praesentium facere atque est!"
        },
        {
            "id": "1003",
            "type": "home",
            "city": {
                "id": "2001",
                "name": "Bogotá",
                "country": "Colombia"
            },
            "address": "Cra. 71 #5a-22 a 5a-84",
            "neighborhood": "Nueva Marsella",
            "lat": "4.628540",
            "lng": "-74.132967",
            "homeStatus": "sale",
            "bedrooms": "4",
            "bathrooms": "3",
            "price": "500000000",
            "area": "146",
            "desc": "Lorem, ipsum dolor sit amet consectetur adipisicing elit. Ipsam voluptatem nam ad doloribus ullam modi? Maxime nam voluptatem harum at iste, esse cum maiores! Distinctio eligendi praesentium facere atque est!"
        },
        {
            "id": "1004",
            "type": "home",
            "city": {
                "id": "2001",
                "name": "Bogotá",
                "country": "Colombia"
            },
            "address": "Cl. 67 #4a-99 a 4a-1",
            "neighborhood": "Nueva Granada",
            "lat": "4.650046",
            "lng": "-74.056505",
            "homeStatus": "sale",
            "bedrooms": "4",
            "bathrooms": "3",
            "price": "500000000",
            "area": "146",
            "desc": "Lorem, ipsum dolor sit amet consectetur adipisicing elit. Ipsam voluptatem nam ad doloribus ullam modi? Maxime nam voluptatem harum at iste, esse cum maiores! Distinctio eligendi praesentium facere atque est!"
        },
        {
            "id": "1005",
            "type": "home",
            "city": {
                "id": "2001",
                "name": "Bogotá",
                "country": "Colombia"
            },
            "address": "Cl. 65 #5-99 a 5-1",
            "neighborhood": "Nueva Granada",
            "lat": "4.648870",
            "lng": "-74.058554",
            "homeStatus": "sale",
            "bedrooms": "4",
            "bathrooms": "3",
            "price": "500000000",
            "area": "146",
            "desc": "Lorem, ipsum dolor sit amet consectetur adipisicing elit. Ipsam voluptatem nam ad doloribus ullam modi? Maxime nam voluptatem harum at iste, esse cum maiores! Distinctio eligendi praesentium facere atque est!"
        },
        {
            "id": "1006",
            "type": "home",
            "city": {
                "id": "2001",
                "name": "Bogotá",
                "country": "Colombia"
            },
            "address": "Cra. 21 #39a-2 a 39a-98",
            "neighborhood": "La Soledad",
            "lat": "4.629318",
            "lng": "-74.074120",
            "homeStatus": "sale",
            "bedrooms": "4",
            "bathrooms": "3",
            "price": "500000000",
            "area": "146",
            "desc": "Lorem, ipsum dolor sit amet consectetur adipisicing elit. Ipsam voluptatem nam ad doloribus ullam modi? Maxime nam voluptatem harum at iste, esse cum maiores! Distinctio eligendi praesentium facere atque est!"
        },
        {
            "id": "1007",
            "type": "home",
            "city": {
                "id": "2001",
                "name": "Bogotá",
                "country": "Colombia"
            },
            "address": "Cl. 39 #28a-87 a 28a-1",
            "neighborhood": "La Soledad",
            "lat": "4.627270",
            "lng": "-74.078462",
            "homeStatus": "sale",
            "bedrooms": "4",
            "bathrooms": "3",
            "price": "500000000",
            "area": "146",
            "desc": "Lorem, ipsum dolor sit amet consectetur adipisicing elit. Ipsam voluptatem nam ad doloribus ullam modi? Maxime nam voluptatem harum at iste, esse cum maiores! Distinctio eligendi praesentium facere atque est!"
        },
        {
            "id": "1008",
            "type": "home",
            "city": {
                "id": "2001",
                "name": "Bogotá",
                "country": "Colombia"
            },
            "address": "Cl. 40 #19-2 a 19-86",
            "neighborhood": "La Soledad",
            "lat": "4.630031",
            "lng": "-74.072815",
            "homeStatus": "sale",
            "bedrooms": "4",
            "bathrooms": "3",
            "price": "500000000",
            "area": "146",
            "desc": "Lorem, ipsum dolor sit amet consectetur adipisicing elit. Ipsam voluptatem nam ad doloribus ullam modi? Maxime nam voluptatem harum at iste, esse cum maiores! Distinctio eligendi praesentium facere atque est!"
        },
        {
            "id": "1009",
            "type": "home",
            "city": {
                "id": "2001",
                "name": "Bogotá",
                "country": "Colombia"
            },
            "address": "Cra. 19b #85-99 a 85-1",
            "neighborhood": "Antiguo Country",
            "lat": "4.672171",
            "lng": "-74.058310",
            "homeStatus": "sale",
            "bedrooms": "4",
            "bathrooms": "3",
            "price": "500000000",
            "area": "146",
            "desc": "Lorem, ipsum dolor sit amet consectetur adipisicing elit. Ipsam voluptatem nam ad doloribus ullam modi? Maxime nam voluptatem harum at iste, esse cum maiores! Distinctio eligendi praesentium facere atque est!"
        },
        {
            "id": "1010",
            "type": "home",
            "city": {
                "id": "2001",
                "name": "Bogotá",
                "country": "Colombia"
            },
            "address": "Cl. 90 #17-28",
            "neighborhood": "Antiguo Country",
            "lat": "4.675235",
            "lng": "-74.054716",
            "homeStatus": "sale",
            "bedrooms": "4",
            "bathrooms": "3",
            "price": "500000000",
            "area": "146",
            "desc": "Lorem, ipsum dolor sit amet consectetur adipisicing elit. Ipsam voluptatem nam ad doloribus ullam modi? Maxime nam voluptatem harum at iste, esse cum maiores! Distinctio eligendi praesentium facere atque est!"
        },
        {
            "id": "1011",
            "type": "home",
            "city": {
                "id": "2001",
                "name": "Bogotá",
                "country": "Colombia"
            },
            "address": "Cra. 16a #76-31",
            "neighborhood": "Antiguo Country",
            "lat": "4.663919",
            "lng": "-74.059971",
            "homeStatus": "sale",
            "bedrooms": "4",
            "bathrooms": "3",
            "price": "500000000",
            "area": "146",
            "desc": "Lorem, ipsum dolor sit amet consectetur adipisicing elit. Ipsam voluptatem nam ad doloribus ullam modi? Maxime nam voluptatem harum at iste, esse cum maiores! Distinctio eligendi praesentium facere atque est!"
        }
        
    ]
}